fracbm/__init__.py
fracbm/cholesky.py
fracbm/daviesharte.py
fracbm/invhurst.py
fracbm/utils.py
fracbm-0.3.0.dist-info/licenses/LICENSE.txt
fracbm-0.3.0.dist-info/METADATA
fracbm-0.3.0.dist-info/WHEEL
fracbm-0.3.0.dist-info/top_level.txt
fracbm-0.3.0.dist-info/RECORD
