Metadata-Version: 2.4
Name: fracbm
Version: 0.3.0
Summary: Fractional Brownian Noise (fGN) and Fractional Brownian Motion (fBM) generators in Python.
Author-email: Harry Brozel <harrybrozel@gmail.com>
License: MIT
Project-URL: Homepage, https://github.com/harry-bro/fracbm
Classifier: Programming Language :: Python :: 3
Classifier: License :: OSI Approved :: MIT License
Classifier: Operating System :: OS Independent
Requires-Python: >=3.8
License-File: LICENSE.txt
Requires-Dist: numpy
Requires-Dist: scipy
Requires-Dist: PyWavelets
Dynamic: license-file
